polars_domain_lookup-0.2.1.dist-info/METADATA
polars_domain_lookup-0.2.1.dist-info/WHEEL
polars_domain_lookup/_internal.pyi
polars_domain_lookup/typing.py
polars_domain_lookup/__init__.py
polars_domain_lookup/_internal.abi3.so
polars_domain_lookup-0.2.1.dist-info/RECORD
