Metadata-Version: 2.4
Name: polars-domain-lookup
Version: 0.2.1
Classifier: Programming Language :: Rust
Classifier: Programming Language :: Python :: Implementation :: CPython
Classifier: Programming Language :: Python :: Implementation :: PyPy
Requires-Dist: polars >=1.8.2
Requires-Python: >=3.8
